LICENSE
MANIFEST.in
README.md
requirements.txt
setup.py
joker/interfaces/__init__.py
joker/interfaces/email.py
joker/interfaces/filesys.py
joker/interfaces/fsi.py
joker/interfaces/http.py
joker/interfaces/monolog.py
joker/interfaces/printable.py
joker/interfaces/repos.py
joker/interfaces/utils.py
joker_interfaces.egg-info/PKG-INFO
joker_interfaces.egg-info/SOURCES.txt
joker_interfaces.egg-info/dependency_links.txt
joker_interfaces.egg-info/namespace_packages.txt
joker_interfaces.egg-info/not-zip-safe
joker_interfaces.egg-info/requires.txt
joker_interfaces.egg-info/top_level.txt