Metadata-Version: 2.1
Name: joker-interfaces
Version: 0.1.5
Summary: Simple interfaces to local file systems and the network.
Home-page: https://github.com/frozflame/joker-interfaces
Author: frozflame
Author-email: frozflame@outlook.com
License: GNU General Public License (GPL)
Keywords: joker
Platform: UNKNOWN
Classifier: Programming Language :: Python
Classifier: Programming Language :: Python :: 3
Classifier: Programming Language :: Python :: 3.5
Classifier: Programming Language :: Python :: 3.6
Classifier: Programming Language :: Python :: 3.7
Classifier: Programming Language :: Python :: 3.8
Classifier: Programming Language :: Python :: 3.9
Classifier: Programming Language :: Python :: 3.10
License-File: LICENSE
